{
  "generated_at": "2026-05-30T09:25:08.228492+00:00",
  "time_window": "QTD from 2026-04-01",
  "qtd_start": "2026-04-01",
  "total_articles": 180,
  "rss_articles": 180,
  "google_news_articles": 0,
  "meltwater_articles": 0,
  "total_mentions": 180,
  "wallets_tracked": 6,
  "primary_brand": "Bitget Wallet",
  "brands": [
    {
      "brand": "Bitget Wallet",
      "mentions": 69,
      "sov": 38.33,
      "rank": 1,
      "color": "#00f0b5",
      "sentiment": {
        "Positive": 43,
        "Neutral": 25,
        "Negative": 1
      },
      "top_narrative": "Stablecoin payments"
    },
    {
      "brand": "MetaMask",
      "mentions": 61,
      "sov": 33.89,
      "rank": 2,
      "color": "#f6851b",
      "sentiment": {
        "Positive": 24,
        "Neutral": 35,
        "Negative": 2
      },
      "top_narrative": "General wallet coverage"
    },
    {
      "brand": "Trust Wallet",
      "mentions": 32,
      "sov": 17.78,
      "rank": 3,
      "color": "#3375bb",
      "sentiment": {
        "Positive": 9,
        "Neutral": 20,
        "Negative": 3
      },
      "top_narrative": "General wallet coverage"
    },
    {
      "brand": "Phantom Wallet",
      "mentions": 8,
      "sov": 4.44,
      "rank": 4,
      "color": "#ab9ff2",
      "sentiment": {
        "Neutral": 4,
        "Positive": 2,
        "Negative": 2
      },
      "top_narrative": "General wallet coverage"
    },
    {
      "brand": "OKX Wallet",
      "mentions": 6,
      "sov": 3.33,
      "rank": 5,
      "color": "#ffffff",
      "sentiment": {
        "Positive": 5,
        "Neutral": 1
      },
      "top_narrative": "AI / agentic finance"
    },
    {
      "brand": "Coinbase Wallet / Base App",
      "mentions": 4,
      "sov": 2.22,
      "rank": 6,
      "color": "#0052ff",
      "sentiment": {
        "Positive": 3,
        "Neutral": 1
      },
      "top_narrative": "General wallet coverage"
    }
  ],
  "sentiment": {
    "Positive": 86,
    "Neutral": 86,
    "Negative": 8
  },
  "primary_sentiment": {
    "Positive": 43,
    "Neutral": 25,
    "Negative": 1
  },
  "narratives": {
    "General wallet coverage": 67,
    "Crypto card": 14,
    "AI / agentic finance": 26,
    "Prediction markets": 10,
    "Onchain trading / swaps": 21,
    "Stablecoin payments": 14,
    "Security": 8,
    "QR payments": 3,
    "Regulation": 6,
    "RWA / tokenized assets": 11
  },
  "narrative_by_brand": {
    "Bitget Wallet": {
      "Onchain trading / swaps": 8,
      "Stablecoin payments": 13,
      "AI / agentic finance": 10,
      "Crypto card": 10,
      "General wallet coverage": 7,
      "QR payments": 2,
      "RWA / tokenized assets": 10,
      "Prediction markets": 9
    },
    "MetaMask": {
      "Crypto card": 4,
      "General wallet coverage": 37,
      "AI / agentic finance": 8,
      "Onchain trading / swaps": 5,
      "Stablecoin payments": 1,
      "Regulation": 4,
      "QR payments": 1,
      "RWA / tokenized assets": 1
    },
    "Trust Wallet": {
      "General wallet coverage": 13,
      "Prediction markets": 1,
      "Onchain trading / swaps": 7,
      "Security": 7,
      "AI / agentic finance": 4
    },
    "Phantom Wallet": {
      "General wallet coverage": 5,
      "AI / agentic finance": 1,
      "Regulation": 2
    },
    "OKX Wallet": {
      "AI / agentic finance": 3,
      "Security": 1,
      "General wallet coverage": 2
    },
    "Coinbase Wallet / Base App": {
      "Onchain trading / swaps": 1,
      "General wallet coverage": 3
    }
  },
  "keyword_cloud": [
    {
      "keyword": "stablecoin",
      "count": 42
    },
    {
      "keyword": "expand",
      "count": 38
    },
    {
      "keyword": "payment",
      "count": 38
    },
    {
      "keyword": "mexc",
      "count": 32
    },
    {
      "keyword": "binance",
      "count": 32
    },
    {
      "keyword": "integration",
      "count": 28
    },
    {
      "keyword": "bring",
      "count": 28
    },
    {
      "keyword": "integrate",
      "count": 28
    },
    {
      "keyword": "asset",
      "count": 26
    },
    {
      "keyword": "acces",
      "count": 26
    },
    {
      "keyword": "card",
      "count": 24
    },
    {
      "keyword": "finance",
      "count": 24
    },
    {
      "keyword": "tokenized",
      "count": 24
    },
    {
      "keyword": "times",
      "count": 22
    },
    {
      "keyword": "partner",
      "count": 22
    },
    {
      "keyword": "hyperliquid",
      "count": 20
    },
    {
      "keyword": "acros",
      "count": 20
    },
    {
      "keyword": "prediction",
      "count": 20
    },
    {
      "keyword": "globenewswire",
      "count": 20
    },
    {
      "keyword": "co-founder",
      "count": 20
    },
    {
      "keyword": "adds",
      "count": 18
    },
    {
      "keyword": "consensy",
      "count": 18
    },
    {
      "keyword": "polymarket",
      "count": 18
    },
    {
      "keyword": "usdcv",
      "count": 18
    },
    {
      "keyword": "network",
      "count": 16
    },
    {
      "keyword": "xstock",
      "count": 16
    },
    {
      "keyword": "briefing",
      "count": 14
    },
    {
      "keyword": "stellar",
      "count": 14
    },
    {
      "keyword": "blockchainreporter",
      "count": 14
    },
    {
      "keyword": "defi",
      "count": 14
    },
    {
      "keyword": "america",
      "count": 14
    },
    {
      "keyword": "stock",
      "count": 14
    },
    {
      "keyword": "societe",
      "count": 14
    },
    {
      "keyword": "coinmarketcap",
      "count": 12
    },
    {
      "keyword": "yahoo",
      "count": 12
    },
    {
      "keyword": "businessinsider",
      "count": 12
    },
    {
      "keyword": "pluang",
      "count": 12
    },
    {
      "keyword": "live",
      "count": 12
    },
    {
      "keyword": "push",
      "count": 12
    },
    {
      "keyword": "latin",
      "count": 12
    },
    {
      "keyword": "agent",
      "count": 12
    },
    {
      "keyword": "generale",
      "count": 12
    },
    {
      "keyword": "mastercard",
      "count": 10
    },
    {
      "keyword": "robinhood",
      "count": 10
    },
    {
      "keyword": "exodu",
      "count": 10
    },
    {
      "keyword": "swap",
      "count": 10
    },
    {
      "keyword": "through",
      "count": 10
    },
    {
      "keyword": "tradingview",
      "count": 10
    },
    {
      "keyword": "everyday",
      "count": 10
    },
    {
      "keyword": "real-world",
      "count": 10
    }
  ],
  "keyword_cloud_by_brand": {
    "Bitget Wallet": [
      {
        "keyword": "expand",
        "count": 36
      },
      {
        "keyword": "payment",
        "count": 28
      },
      {
        "keyword": "card",
        "count": 20
      },
      {
        "keyword": "tokenized",
        "count": 20
      },
      {
        "keyword": "integration",
        "count": 18
      },
      {
        "keyword": "globenewswire",
        "count": 18
      },
      {
        "keyword": "polymarket",
        "count": 18
      },
      {
        "keyword": "acros",
        "count": 16
      },
      {
        "keyword": "xstock",
        "count": 16
      },
      {
        "keyword": "acces",
        "count": 16
      },
      {
        "keyword": "prediction",
        "count": 16
      },
      {
        "keyword": "finance",
        "count": 14
      },
      {
        "keyword": "integrate",
        "count": 14
      },
      {
        "keyword": "stellar",
        "count": 14
      },
      {
        "keyword": "mexc",
        "count": 14
      },
      {
        "keyword": "america",
        "count": 14
      },
      {
        "keyword": "bring",
        "count": 12
      },
      {
        "keyword": "stablecoin",
        "count": 12
      },
      {
        "keyword": "partner",
        "count": 12
      },
      {
        "keyword": "latin",
        "count": 12
      },
      {
        "keyword": "exodu",
        "count": 10
      },
      {
        "keyword": "swap",
        "count": 10
      },
      {
        "keyword": "businessinsider",
        "count": 10
      },
      {
        "keyword": "pluang",
        "count": 10
      },
      {
        "keyword": "times",
        "count": 10
      },
      {
        "keyword": "real-world",
        "count": 10
      },
      {
        "keyword": "joins",
        "count": 10
      },
      {
        "keyword": "adds",
        "count": 10
      },
      {
        "keyword": "stock",
        "count": 10
      },
      {
        "keyword": "africa",
        "count": 10
      },
      {
        "keyword": "through",
        "count": 8
      },
      {
        "keyword": "network",
        "count": 8
      },
      {
        "keyword": "everyday",
        "count": 8
      },
      {
        "keyword": "asset",
        "count": 8
      },
      {
        "keyword": "realgo",
        "count": 8
      }
    ],
    "MetaMask": [
      {
        "keyword": "stablecoin",
        "count": 30
      },
      {
        "keyword": "co-founder",
        "count": 20
      },
      {
        "keyword": "consensy",
        "count": 18
      },
      {
        "keyword": "usdcv",
        "count": 18
      },
      {
        "keyword": "societe",
        "count": 14
      },
      {
        "keyword": "generale",
        "count": 12
      },
      {
        "keyword": "mastercard",
        "count": 10
      },
      {
        "keyword": "robinhood",
        "count": 10
      },
      {
        "keyword": "finance",
        "count": 10
      },
      {
        "keyword": "mexc",
        "count": 10
      },
      {
        "keyword": "socgen",
        "count": 10
      },
      {
        "keyword": "bring",
        "count": 8
      },
      {
        "keyword": "aave",
        "count": 8
      },
      {
        "keyword": "partner",
        "count": 8
      },
      {
        "keyword": "defi",
        "count": 8
      },
      {
        "keyword": "times",
        "count": 8
      },
      {
        "keyword": "finlay",
        "count": 8
      },
      {
        "keyword": "years",
        "count": 8
      },
      {
        "keyword": "integrate",
        "count": 8
      },
      {
        "keyword": "coinmarketcap",
        "count": 6
      },
      {
        "keyword": "open",
        "count": 6
      },
      {
        "keyword": "transaction",
        "count": 6
      },
      {
        "keyword": "layer",
        "count": 6
      },
      {
        "keyword": "fireblock",
        "count": 6
      },
      {
        "keyword": "yahoo",
        "count": 6
      },
      {
        "keyword": "briefing",
        "count": 6
      },
      {
        "keyword": "payment",
        "count": 6
      },
      {
        "keyword": "feature",
        "count": 6
      },
      {
        "keyword": "asset",
        "count": 6
      },
      {
        "keyword": "mica-compliant",
        "count": 6
      },
      {
        "keyword": "adds",
        "count": 6
      },
      {
        "keyword": "leave",
        "count": 6
      },
      {
        "keyword": "binance",
        "count": 6
      },
      {
        "keyword": "sg-forge",
        "count": 6
      },
      {
        "keyword": "card",
        "count": 4
      }
    ],
    "Trust Wallet": [
      {
        "keyword": "binance",
        "count": 20
      },
      {
        "keyword": "hyperliquid",
        "count": 14
      },
      {
        "keyword": "integration",
        "count": 10
      },
      {
        "keyword": "bring",
        "count": 8
      },
      {
        "keyword": "contract",
        "count": 6
      },
      {
        "keyword": "live",
        "count": 6
      },
      {
        "keyword": "usdt",
        "count": 6
      },
      {
        "keyword": "asset",
        "count": 6
      },
      {
        "keyword": "perp",
        "count": 6
      },
      {
        "keyword": "mobile",
        "count": 6
      },
      {
        "keyword": "india",
        "count": 6
      },
      {
        "keyword": "economy",
        "count": 4
      },
      {
        "keyword": "perpetual",
        "count": 4
      },
      {
        "keyword": "tradingview",
        "count": 4
      },
      {
        "keyword": "openpr",
        "count": 4
      },
      {
        "keyword": "platform",
        "count": 4
      },
      {
        "keyword": "token",
        "count": 4
      },
      {
        "keyword": "x402",
        "count": 4
      },
      {
        "keyword": "payment",
        "count": 4
      },
      {
        "keyword": "integrate",
        "count": 4
      },
      {
        "keyword": "agent",
        "count": 4
      },
      {
        "keyword": "briefing",
        "count": 4
      },
      {
        "keyword": "cryptonew",
        "count": 4
      },
      {
        "keyword": "rachel",
        "count": 4
      },
      {
        "keyword": "conlan",
        "count": 4
      },
      {
        "keyword": "interim",
        "count": 4
      },
      {
        "keyword": "mesh",
        "count": 4
      },
      {
        "keyword": "executive",
        "count": 4
      },
      {
        "keyword": "consensu",
        "count": 4
      },
      {
        "keyword": "miami",
        "count": 4
      },
      {
        "keyword": "scam",
        "count": 4
      },
      {
        "keyword": "fake",
        "count": 4
      },
      {
        "keyword": "verification",
        "count": 4
      },
      {
        "keyword": "issue",
        "count": 4
      },
      {
        "keyword": "advisory",
        "count": 4
      }
    ],
    "Phantom Wallet": [
      {
        "keyword": "asset",
        "count": 4
      },
      {
        "keyword": "cftc",
        "count": 4
      },
      {
        "keyword": "outage",
        "count": 4
      },
      {
        "keyword": "spark",
        "count": 4
      },
      {
        "keyword": "disruption",
        "count": 4
      },
      {
        "keyword": "display",
        "count": 4
      },
      {
        "keyword": "rabby",
        "count": 2
      },
      {
        "keyword": "messari",
        "count": 2
      },
      {
        "keyword": "failed",
        "count": 2
      },
      {
        "keyword": "mexc",
        "count": 2
      },
      {
        "keyword": "wins",
        "count": 2
      },
      {
        "keyword": "approval",
        "count": 2
      },
      {
        "keyword": "derivative",
        "count": 2
      },
      {
        "keyword": "acces",
        "count": 2
      },
      {
        "keyword": "coinmarketcap",
        "count": 2
      },
      {
        "keyword": "what",
        "count": 2
      },
      {
        "keyword": "binance",
        "count": 2
      },
      {
        "keyword": "lock",
        "count": 2
      },
      {
        "keyword": "phantom-style",
        "count": 2
      },
      {
        "keyword": "protection",
        "count": 2
      },
      {
        "keyword": "concern",
        "count": 2
      },
      {
        "keyword": "service",
        "count": 2
      },
      {
        "keyword": "cause",
        "count": 2
      },
      {
        "keyword": "widespread",
        "count": 2
      },
      {
        "keyword": "balance",
        "count": 2
      },
      {
        "keyword": "error",
        "count": 2
      },
      {
        "keyword": "cryptorank",
        "count": 2
      },
      {
        "keyword": "cryptocurrency",
        "count": 2
      },
      {
        "keyword": "grapple",
        "count": 2
      },
      {
        "keyword": "brief",
        "count": 2
      },
      {
        "keyword": "operational",
        "count": 2
      },
      {
        "keyword": "affecting",
        "count": 2
      },
      {
        "keyword": "crowdfund",
        "count": 2
      },
      {
        "keyword": "insider",
        "count": 2
      },
      {
        "keyword": "token",
        "count": 2
      }
    ],
    "OKX Wallet": [
      {
        "keyword": "network",
        "count": 6
      },
      {
        "keyword": "stake",
        "count": 6
      },
      {
        "keyword": "blockchainreporter",
        "count": 4
      },
      {
        "keyword": "security",
        "count": 4
      },
      {
        "keyword": "web3",
        "count": 4
      },
      {
        "keyword": "mexc",
        "count": 4
      },
      {
        "keyword": "pharo",
        "count": 4
      },
      {
        "keyword": "before",
        "count": 4
      },
      {
        "keyword": "agentic",
        "count": 2
      },
      {
        "keyword": "autonomou",
        "count": 2
      },
      {
        "keyword": "on-chain",
        "count": 2
      },
      {
        "keyword": "asset",
        "count": 2
      },
      {
        "keyword": "management",
        "count": 2
      },
      {
        "keyword": "collaborate",
        "count": 2
      },
      {
        "keyword": "goplu",
        "count": 2
      },
      {
        "keyword": "power",
        "count": 2
      },
      {
        "keyword": "safeguard",
        "count": 2
      },
      {
        "keyword": "multi-chain",
        "count": 2
      },
      {
        "keyword": "application",
        "count": 2
      },
      {
        "keyword": "decentralized",
        "count": 2
      },
      {
        "keyword": "officially",
        "count": 2
      },
      {
        "keyword": "integrated",
        "count": 2
      },
      {
        "keyword": "hokanew",
        "count": 2
      },
      {
        "keyword": "integrate",
        "count": 2
      },
      {
        "keyword": "accelerate",
        "count": 2
      },
      {
        "keyword": "staking",
        "count": 2
      },
      {
        "keyword": "adoption",
        "count": 2
      },
      {
        "keyword": "among",
        "count": 2
      },
      {
        "keyword": "communitie",
        "count": 2
      },
      {
        "keyword": "partner",
        "count": 2
      },
      {
        "keyword": "exclusively",
        "count": 2
      },
      {
        "keyword": "mainnet",
        "count": 2
      },
      {
        "keyword": "enjoy",
        "count": 2
      },
      {
        "keyword": "annual",
        "count": 2
      },
      {
        "keyword": "percentage",
        "count": 2
      }
    ],
    "Coinbase Wallet / Base App": [
      {
        "keyword": "signal",
        "count": 4
      },
      {
        "keyword": "push",
        "count": 4
      },
      {
        "keyword": "toward",
        "count": 4
      },
      {
        "keyword": "meme",
        "count": 2
      },
      {
        "keyword": "coin",
        "count": 2
      },
      {
        "keyword": "memes",
        "count": 2
      },
      {
        "keyword": "defy",
        "count": 2
      },
      {
        "keyword": "slide",
        "count": 2
      },
      {
        "keyword": "pump",
        "count": 2
      },
      {
        "keyword": "double",
        "count": 2
      },
      {
        "keyword": "down",
        "count": 2
      },
      {
        "keyword": "trading",
        "count": 2
      },
      {
        "keyword": "coinmarketcap",
        "count": 2
      },
      {
        "keyword": "cryptonew",
        "count": 2
      },
      {
        "keyword": "tease",
        "count": 2
      },
      {
        "keyword": "all-in-one",
        "count": 2
      },
      {
        "keyword": "mass",
        "count": 2
      },
      {
        "keyword": "adoption",
        "count": 2
      },
      {
        "keyword": "live",
        "count": 2
      },
      {
        "keyword": "bitcoin",
        "count": 2
      },
      {
        "keyword": "coinfomania",
        "count": 2
      }
    ]
  },
  "top_sources": [
    [
      "MEXC",
      15
    ],
    [
      "Bitget",
      12
    ],
    [
      "GlobeNewswire",
      10
    ],
    [
      "The Crypto Times",
      8
    ],
    [
      "Binance",
      8
    ],
    [
      "Crypto Briefing",
      7
    ],
    [
      "BlockchainReporter",
      7
    ],
    [
      "CoinMarketCap",
      6
    ],
    [
      "Yahoo Finance",
      6
    ],
    [
      "markets.businessinsider.com",
      6
    ],
    [
      "Pluang",
      6
    ],
    [
      "TradingView",
      5
    ],
    [
      "Crypto Economy",
      4
    ],
    [
      "openPR.com",
      4
    ],
    [
      "U.Today",
      3
    ]
  ],
  "competitor_intelligence": [
    {
      "brand": "MetaMask",
      "tagline": "Incumbent self-custody and distribution benchmark",
      "threat_level": "HIGH",
      "rank": 2,
      "mentions": 61,
      "positive": 24,
      "negative": 2,
      "tier1": 2,
      "top_narrative": "General wallet coverage",
      "latest_articles": [
        {
          "date": "2026-05-29T15:09:07+00:00",
          "headline": "MetaMask and Mastercard Launch Self-Custody Crypto Card Across U.S. - CoinMarketCap",
          "source": "CoinMarketCap",
          "url": "https://news.google.com/rss/articles/CBMiqwFBVV95cUxPdEliWHFSdjBoaDhNWmVGRUlaZWJIeFpPVFJPTng0ZDlJcTBHN2w1cThkLUt4M0Y3SXdnQmtvX1A5OFgwbkgwb0RtQTlQYmZiSGR0SUhoMWlTaENIRm5rVThBNW1zOG1fRjFmUWtDZ1EzY19wd0pvbW5CR0prd0ZQSVNERFNpblhaRFpMM3JPQmxTeTBScl95SUc2dzFsXzJtX2ZFNXRpLW9iWWM?oc=5",
          "narrative": "Crypto card",
          "sentiment": "Positive"
        },
        {
          "date": "2026-05-29T14:45:00+00:00",
          "headline": "Open Transaction Layer Launches With Fireblocks, Robinhood and MetaMask Backing - Yahoo Finance",
          "source": "Yahoo Finance",
          "url": "https://news.google.com/rss/articles/CBMiqwFBVV95cUxPeml0eGJDUjVHMzZKMnFFc1hvdk04aDNHZHJOUWlEZXRWclNKSXdxMjdYZ0dCa3RRSzdOYjBjV3NuUjZ4Wi1PQUhBOHJDeHJSVkxjRUs1S3JkaVN0Yzl0MGQ3bHZIZllEclM3N0x4eU0zUTNWd3IxeGJyRUNjX3VXcW9IOU1QVEVfa1hoMFdtVEkzdlFGUlc4ZUFFc2oyMXpRR2pqWGdHM2t6aEk?oc=5",
          "narrative": "General wallet coverage",
          "sentiment": "Positive"
        },
        {
          "date": "2026-05-29T13:43:00+00:00",
          "headline": "MetaMask is Making Big Moves as the New Brokerage Hub - Tokenist",
          "source": "Tokenist",
          "url": "https://news.google.com/rss/articles/CBMickFVX3lxTE1aS0FPRlJXVERaYVdXYzNZd0dDQldqYl9EZDZpamxHWVFnMHdYT2pDNkJITjZuWjdKVC0wbGpCb2pvQlpqa1BSOWIwX2p0cHBKRnpvd0lFYVFPVjZ5SnZOVTdnXzRXbWFCcXg0V3o5X0s0QQ?oc=5",
          "narrative": "General wallet coverage",
          "sentiment": "Positive"
        }
      ],
      "verdict": "Lower direct narrative overlap, but 2 higher-impact article(s) make this worth monitoring for category perception. Sentiment skews constructive, suggesting room for proactive counter-positioning."
    },
    {
      "brand": "Trust Wallet",
      "tagline": "Retail scale and wallet UX challenger",
      "threat_level": "HIGH",
      "rank": 3,
      "mentions": 32,
      "positive": 9,
      "negative": 3,
      "tier1": 1,
      "top_narrative": "General wallet coverage",
      "latest_articles": [
        {
          "date": "2026-05-29T16:35:24+00:00",
          "headline": "Hyperliquid HIP‑4 Outcome Contracts Launch on Trust Wallet - Crypto Economy",
          "source": "Crypto Economy",
          "url": "https://news.google.com/rss/articles/CBMijwFBVV95cUxOYzgzcVZRMG1pSnVET19zWDNHOGdlNWVxdHlwaXJYZTJGNjJyUGg0LTlEZUFnVF83MlVtbHNDVGVTc1UwMk8zM0xCMjQ2VlhkNnNjRG1GaV96UEt2RHU3Ym9RTHFkbGJ0RlV4X1llSTByNFh5WFZWcTdWaVJhVmpGMU90VFhoOGM2RWpXSG9mYw?oc=5",
          "narrative": "General wallet coverage",
          "sentiment": "Positive"
        },
        {
          "date": "2026-05-28T21:50:38+00:00",
          "headline": "Trust Wallet completes integration with Hyperliquid perpetual contracts and HIP-4 prediction markets - Bitget",
          "source": "Bitget",
          "url": "https://news.google.com/rss/articles/CBMiXkFVX3lxTE1yZlhLYnhiY0VZQkxnRmNJa1pBdFdvWHZ0Sndqa0NDcEU4OWlTdzN2T3F6YTZJdHRJWHdDeFJSaF9xZWJxcUpvOEptSWh5X2VuSFJxdEJlcnlHckFIMnfSAWNBVV95cUxNc1QxTGpCb05BREJjeUlFMnNxWnJsbkJJeTEzUUVsUlJjZFhZX1dwd2REdVFLbXBkbVVMdXhWVVliX1NnNFNrdTlNU1Z4X250dEJJdEd4eWg4RTlraGtsZzF2UUE?oc=5",
          "narrative": "Prediction markets",
          "sentiment": "Neutral"
        },
        {
          "date": "2026-05-28T14:15:11+00:00",
          "headline": "Trust Wallet Added PnL Cards to Trades - TradingView",
          "source": "TradingView",
          "url": "https://news.google.com/rss/articles/CBMinAFBVV95cUxNRWtzcEtEYUtxMmZ5LXdEaHVNeU1ibTFHRmpxNHg3ZU80QXQ2MXBXeXZVZXdoRzlrNDROWkZPTEttQ29ZWUQ1cDRvcTBuOVR5WDNuYjFQdWNJejVGVHFUbGNBVjdQMVpNQzc1LVpkM3FhOG1KREVUd2VKRXM4ck1OdFI3QU1xWjBZUmR3ejRzVkYtcXRERFZJVk5CSko?oc=5",
          "narrative": "Onchain trading / swaps",
          "sentiment": "Neutral"
        }
      ],
      "verdict": "Lower direct narrative overlap, but 1 higher-impact article(s) make this worth monitoring for category perception. Sentiment skews constructive, suggesting room for proactive counter-positioning."
    },
    {
      "brand": "OKX Wallet",
      "tagline": "Exchange-backed Web3 wallet and DEX thesis",
      "threat_level": "HIGH",
      "rank": 5,
      "mentions": 6,
      "positive": 5,
      "negative": 0,
      "tier1": 0,
      "top_narrative": "AI / agentic finance",
      "latest_articles": [
        {
          "date": "2026-05-25T07:00:32+00:00",
          "headline": "OKX Wallet Launches Agentic Wallet For Autonomous On-chain Asset Management - BlockchainReporter",
          "source": "BlockchainReporter",
          "url": "https://news.google.com/rss/articles/CBMiqwFBVV95cUxQNEtKQ0lXZ1dLbUFmTjZnZlF1eW1SRUNablNWamFMaFJvaVg5NUo2a1VpcTZMeVBxc2p1T2xrVkNhZ3ZSOGdvYzdwTTkzZTNpSUduekVRSzFFNWM0ZFJkY3pVdzZqR0NVSHVBRmE2VmdxVVBYcnlvUmdNMGtOU2xORUF6VE1WWjhYbmZKTDRrODlmRjlSRWxqVER3SG54bmNIRXA1ei1ieHNrQXM?oc=5",
          "narrative": "AI / agentic finance",
          "sentiment": "Positive"
        },
        {
          "date": "2026-05-19T11:01:42+00:00",
          "headline": "OKX Wallet Collaborates With GoPlus Security To Power Safeguards of Web3 Multi-Chain Applications With Decentralized Security - MEXC",
          "source": "MEXC",
          "url": "https://news.google.com/rss/articles/CBMiSEFVX3lxTE9uY3ZtQndYTmVMYjhVX05ZcVd2c21kMHIzSFNub2Q2R0dSNzJ4a3JZZkNCRG91LVk3RDctOGMyamd5dHpSUlNIbg?oc=5",
          "narrative": "Security",
          "sentiment": "Positive"
        },
        {
          "date": "2026-05-15T07:00:00+00:00",
          "headline": "Pi Network Officially Integrated Into OKX Wallet - HOKANEWS.COM",
          "source": "HOKANEWS.COM",
          "url": "https://news.google.com/rss/articles/CBMigAFBVV95cUxOajlWNUc2aUNJSy1EU3JXc0R2bWF2MGZHUUZKbFRmZUQ2MUwzeThYVUhIdXA3dFRJdG0tWnlTRGVZTFBrTnZfZC1ySUdvRHB1RmxhUGJGd1pXQ2lJdjE4a2hGc2ZjTFh2eTdqWFNCbzkydzZrWnpBMGhWeWliNXRraA?oc=5",
          "narrative": "General wallet coverage",
          "sentiment": "Positive"
        }
      ],
      "verdict": "Owns visibility around ai / agentic finance, a strategically relevant wallet narrative. Useful benchmark for Bitget Wallet proof points and media hooks. Sentiment skews constructive, suggesting room for proactive counter-positioning."
    },
    {
      "brand": "Phantom Wallet",
      "tagline": "Solana-native wallet expanding cross-chain",
      "threat_level": "MONITOR",
      "rank": 4,
      "mentions": 8,
      "positive": 2,
      "negative": 2,
      "tier1": 0,
      "top_narrative": "General wallet coverage",
      "latest_articles": [
        {
          "date": "2026-05-25T07:00:00+00:00",
          "headline": "Rabby Wallet vs Phantom - Messari",
          "source": "Messari",
          "url": "https://news.google.com/rss/articles/CBMiaEFVX3lxTE9HT1RVTUNZT2k3blBGTU5RNHB0SUZLUWx1RFBROTk2ekxncFpWZVJjWmF4U3RHRkJVUERhdTJDOElmcGNlVUdBLVgydFkzdEJHNmpoSUJqaGlSY0tHeEgtOHVVOXBjNVZ2?oc=5",
          "narrative": "General wallet coverage",
          "sentiment": "Neutral"
        },
        {
          "date": "2026-05-22T08:24:05+00:00",
          "headline": "Phantom Wallet Failed to Get Assets: 2026 Fix Guide - MEXC",
          "source": "MEXC",
          "url": "https://news.google.com/rss/articles/CBMiSEFVX3lxTE9YRHVHT3FmVmQ4S2JHTEFaZlpidEs2QTYxNFN5U3ZGMzFQald6RHdpeHFfS0RGVDdQazdwQnh3Y3J0LVNSSHM2SQ?oc=5",
          "narrative": "AI / agentic finance",
          "sentiment": "Neutral"
        },
        {
          "date": "2026-05-20T21:09:37+00:00",
          "headline": "Phantom Wallet Wins CFTC Approval for Derivatives Access - CoinMarketCap",
          "source": "CoinMarketCap",
          "url": "https://news.google.com/rss/articles/CBMinwFBVV95cUxNRWFDZGFrN1dDU0JvZUZEbUk2OVBZU25sQUlnc3RoRmdVV0JGU2J1ZFZndk1NLVFBOFpLSGIzTENDX0pub1NuQkZ3aHhfay1meVBBVzltMEJqRC12OU1SSUdQQUFWWk9vMVkxcmdjem5mbnVaYWt2WTBPbnBRd1RqUlVXNFVxV0pyNXFxNDlYeEt3YTgzdFJDaXM1ZnpvLVk?oc=5",
          "narrative": "Regulation",
          "sentiment": "Positive"
        }
      ],
      "verdict": "Coverage is present but mostly broad wallet/category news. Lower immediate threat unless volume accelerates."
    },
    {
      "brand": "Coinbase Wallet / Base App",
      "tagline": "US-regulated wallet and Base ecosystem gateway",
      "threat_level": "LOW",
      "rank": 6,
      "mentions": 4,
      "positive": 3,
      "negative": 0,
      "tier1": 0,
      "top_narrative": "General wallet coverage",
      "latest_articles": [
        {
          "date": "2026-05-25T06:19:20+00:00",
          "headline": "Meme Coin News: Memes Defy SOL Slide as Pump.fun and Base App Double Down on Trading - CoinMarketCap",
          "source": "CoinMarketCap",
          "url": "https://news.google.com/rss/articles/CBMiwgFBVV95cUxOUXpQN0ZFREV5M2NxcGM1dXJuaW54dGo4S0h6MUdBRlZyUE40WVptVGdYVE9XMVB6cElVV05jQTdvUTBHMGxPTkpQR245a0o5dzF4MkJKTk9FU1JPZTREV3IzYTZTdkNna2tjczBwcVhIQlZ5b0lnTFUtZk9NTkxQaXA0NzZvZ2QwSUVEd1AwcVRjNnNKeWdUeE9obUw3X0piblJkQV9rajg5clFtdVFyRzI1Z1VfZlhBd0ptcFJqcFpUdw?oc=5",
          "narrative": "Onchain trading / swaps",
          "sentiment": "Positive"
        },
        {
          "date": "2026-04-04T07:00:00+00:00",
          "headline": "Coinbase CEO Signals Base App Push Toward 1B Crypto Users - Cryptonews.net",
          "source": "Cryptonews.net",
          "url": "https://news.google.com/rss/articles/CBMiV0FVX3lxTE5IQzdNNmtqUVZUam9XOFp6SkF3YTl4Mm1HVkEtLTVsRFJ2bWN0bjRiYjYxRGlHT1JzVWZ6V1BfRDNmTDkxWnhLWUhPN2hUeFF4dWt4dDNlVQ?oc=5",
          "narrative": "General wallet coverage",
          "sentiment": "Positive"
        },
        {
          "date": "2026-04-04T07:00:00+00:00",
          "headline": "Coinbase CEO Teases All-in-One Base App for Mass Crypto Adoption - Live Bitcoin News",
          "source": "Live Bitcoin News",
          "url": "https://news.google.com/rss/articles/CBMingFBVV95cUxPazd3cUM2bERxS1BEaHd4SzNiWDFvLWhwTGVFM1NpTXUzWWdaTnJIaTczVmt0MVVWdnlweHJVQnhsYjRrVlRsYnlaaW5ld0NsMnNVMmFxVmtnLVZYSjJZcXJfYUhnWEdVb2pJU21CS1FxSWdRNmM1dE1nUU1FNlhBNF9uRkRDdUFCS05lQ3VuMVNaZmhRYmp2T3hCbDUydw?oc=5",
          "narrative": "General wallet coverage",
          "sentiment": "Positive"
        }
      ],
      "verdict": "Coverage is present but mostly broad wallet/category news. Lower immediate threat unless volume accelerates."
    }
  ],
  "last_24h": {
    "articles": [
      {
        "date": "2026-05-29T16:35:24+00:00",
        "source": "Crypto Economy",
        "headline": "Hyperliquid HIP‑4 Outcome Contracts Launch on Trust Wallet - Crypto Economy",
        "url": "https://news.google.com/rss/articles/CBMijwFBVV95cUxOYzgzcVZRMG1pSnVET19zWDNHOGdlNWVxdHlwaXJYZTJGNjJyUGg0LTlEZUFnVF83MlVtbHNDVGVTc1UwMk8zM0xCMjQ2VlhkNnNjRG1GaV96UEt2RHU3Ym9RTHFkbGJ0RlV4X1llSTByNFh5WFZWcTdWaVJhVmpGMU90VFhoOGM2RWpXSG9mYw?oc=5",
        "brand": "Trust Wallet",
        "narrative": "General wallet coverage",
        "sentiment": "Positive"
      },
      {
        "date": "2026-05-29T15:09:07+00:00",
        "source": "CoinMarketCap",
        "headline": "MetaMask and Mastercard Launch Self-Custody Crypto Card Across U.S. - CoinMarketCap",
        "url": "https://news.google.com/rss/articles/CBMiqwFBVV95cUxPdEliWHFSdjBoaDhNWmVGRUlaZWJIeFpPVFJPTng0ZDlJcTBHN2w1cThkLUt4M0Y3SXdnQmtvX1A5OFgwbkgwb0RtQTlQYmZiSGR0SUhoMWlTaENIRm5rVThBNW1zOG1fRjFmUWtDZ1EzY19wd0pvbW5CR0prd0ZQSVNERFNpblhaRFpMM3JPQmxTeTBScl95SUc2dzFsXzJtX2ZFNXRpLW9iWWM?oc=5",
        "brand": "MetaMask",
        "narrative": "Crypto card",
        "sentiment": "Positive"
      },
      {
        "date": "2026-05-29T14:45:00+00:00",
        "source": "Yahoo Finance",
        "headline": "Open Transaction Layer Launches With Fireblocks, Robinhood and MetaMask Backing - Yahoo Finance",
        "url": "https://news.google.com/rss/articles/CBMiqwFBVV95cUxPeml0eGJDUjVHMzZKMnFFc1hvdk04aDNHZHJOUWlEZXRWclNKSXdxMjdYZ0dCa3RRSzdOYjBjV3NuUjZ4Wi1PQUhBOHJDeHJSVkxjRUs1S3JkaVN0Yzl0MGQ3bHZIZllEclM3N0x4eU0zUTNWd3IxeGJyRUNjX3VXcW9IOU1QVEVfa1hoMFdtVEkzdlFGUlc4ZUFFc2oyMXpRR2pqWGdHM2t6aEk?oc=5",
        "brand": "MetaMask",
        "narrative": "General wallet coverage",
        "sentiment": "Positive"
      },
      {
        "date": "2026-05-29T13:43:00+00:00",
        "source": "Tokenist",
        "headline": "MetaMask is Making Big Moves as the New Brokerage Hub - Tokenist",
        "url": "https://news.google.com/rss/articles/CBMickFVX3lxTE1aS0FPRlJXVERaYVdXYzNZd0dDQldqYl9EZDZpamxHWVFnMHdYT2pDNkJITjZuWjdKVC0wbGpCb2pvQlpqa1BSOWIwX2p0cHBKRnpvd0lFYVFPVjZ5SnZOVTdnXzRXbWFCcXg0V3o5X0s0QQ?oc=5",
        "brand": "MetaMask",
        "narrative": "General wallet coverage",
        "sentiment": "Positive"
      },
      {
        "date": "2026-05-29T11:49:11+00:00",
        "source": "FinanceFeeds",
        "headline": "Robinhood, eToro, MetaMask Back Open Transaction Layer As Onchain Finance Tries To Fix Its Coordination Problem - FinanceFeeds",
        "url": "https://news.google.com/rss/articles/CBMi0AFBVV95cUxQeW5lT3hwaGpaN3I5OHl2QXNPanlvQlJVWUJZa2pkNFZFSDUyZkJDa19NZVR5QVkxUjM5RnY4UExSelhmWHdyOWZCZ0d1bHAyTTN2d2dQVzFqTlctMXRqRE8zX0o3aThjdGJlNEtEM2dVWjBXbXpDQ1FOcUtWSG1sOEw1dEFmSU5QQ1VPQ3djeXZReTBBclBHaEdidUtuU081VjVFX3FDb3JDd2E5dnFfVUVhMDBBdFVKTnFPam1US0JFRXF4dHI2M0FJMXh0Wkp4?oc=5",
        "brand": "MetaMask",
        "narrative": "AI / agentic finance",
        "sentiment": "Neutral"
      }
    ],
    "narratives": {
      "General wallet coverage": 3,
      "Crypto card": 1,
      "AI / agentic finance": 1
    },
    "brands": {
      "Trust Wallet": 1,
      "MetaMask": 4
    }
  }
}